thrift_hive_metastore/__init__.py
thrift_hive_metastore/constants.py
thrift_hive_metastore/ThriftHiveMetastore-remote.py
thrift_hive_metastore/ttypes.py
thrift_hive_metastore/ThriftHiveMetastore.py
fb303/__init__.py
fb303/constants.py
fb303/FacebookService.py
fb303/FacebookService-remote.py
fb303/ttypes.py
thrift_hive_metastore-1.0.0.dist-info/top_level.txt
thrift_hive_metastore-1.0.0.dist-info/DESCRIPTION.rst
thrift_hive_metastore-1.0.0.dist-info/metadata.json
thrift_hive_metastore-1.0.0.dist-info/WHEEL
thrift_hive_metastore-1.0.0.dist-info/RECORD
thrift_hive_metastore-1.0.0.dist-info/METADATA
thrift_hive_metastore-1.0.0.dist-info/entry_points.txt
