Metadata-Version: 2.0
Name: thrift-hive-metastore
Version: 1.0.0
Summary: A thrift client of hive metestore
Home-page: https://github.com/oreh/thrift_hive_metastore
Author: oreh
Author-email: herolxh@gmail.com
License: MIT
Keywords: thrift hive metastore
Platform: UNKNOWN
Classifier: Development Status :: 3 - Alpha
Classifier: Intended Audience :: Developers
Classifier: Topic :: Software Development :: Build Tools
Classifier: License :: OSI Approved :: MIT License
Classifier: Programming Language :: Python :: 2
Classifier: Programming Language :: Python :: 2.6
Classifier: Programming Language :: Python :: 2.7
Requires-Dist: thrift
Provides-Extra: test
Requires-Dist: coverage; extra == 'test'
Provides-Extra: dev
Requires-Dist: check-manifest; extra == 'dev'
